requests_http_message_signatures/__init__.py
requests_http_message_signatures-0.3.1.dist-info/LICENSE
requests_http_message_signatures-0.3.1.dist-info/WHEEL
requests_http_message_signatures-0.3.1.dist-info/METADATA
requests_http_message_signatures-0.3.1.dist-info/RECORD
