Metadata-Version: 2.1
Name: requests-http-message-signatures
Version: 0.3.1
Summary: A request authentication plugin implementing IETF HTTP Message Signatures
Home-page: https://dev.funkwhale.audio/funkwhale/requests-http-message-signatures
License: Apache-2.0
Author: Andrey Kislyuk
Requires-Python: >=3.7,<4.0
Classifier: Development Status :: 5 - Production/Stable
Classifier: Intended Audience :: Developers
Classifier: License :: OSI Approved :: Apache Software License
Classifier: Operating System :: MacOS :: MacOS X
Classifier: Operating System :: POSIX
Classifier: Programming Language :: Python
Classifier: Programming Language :: Python :: 3
Classifier: Programming Language :: Python :: 3.10
Classifier: Programming Language :: Python :: 3.7
Classifier: Programming Language :: Python :: 3.8
Classifier: Programming Language :: Python :: 3.9
Classifier: Topic :: Software Development :: Libraries :: Python Modules
Requires-Dist: cryptography (>=1.8.2)
Requires-Dist: requests (>=2,<3)
